flask_pundit/__init__.py
flask_pundit/application_policy.py
flask_pundit/helpers.py
tests/models/__init__.py
tests/models/comment.py
tests/models/post.py
tests/policies/__init__.py
tests/policies/commenting.py
tests/policies/post.py
flask_pundit-1.2.2.dist-info/LICENSE
flask_pundit-1.2.2.dist-info/METADATA
flask_pundit-1.2.2.dist-info/WHEEL
flask_pundit-1.2.2.dist-info/top_level.txt
flask_pundit-1.2.2.dist-info/RECORD
