Metadata-Version: 2.1
Name: flask-pundit
Version: 1.2.2
Summary: Simple library to manage resource authorization and scoping
Home-page: https://github.com/anurag90x/flask-pundit
Author: Anurag Chaudhury
Author-email: anuragchaudhury@gmail.com
License: MIT
Platform: any
Classifier: Framework :: Flask
Classifier: Programming Language :: Python :: 2.6
Classifier: Programming Language :: Python :: 2.7
Classifier: Programming Language :: Python :: 3.7
Classifier: License :: OSI Approved :: MIT License
Requires-Dist: Flask (<2,>=1.0.2)
